alphaneural/__init__.py
alphaneural/alphaneural.py
alphaneural-0.0.5.dist-info/LICENSE
alphaneural-0.0.5.dist-info/METADATA
alphaneural-0.0.5.dist-info/WHEEL
alphaneural-0.0.5.dist-info/top_level.txt
alphaneural-0.0.5.dist-info/RECORD
