Metadata-Version: 2.1
Name: alphaneural
Version: 0.0.5
Summary: A package for predicting buy and sell signals based on alphaneural for quants
Home-page: https://nkrtech.com
Download-URL: https://github.com/moinonin/alphaneural/archive/refs/heads/main.zip
Author: Nicolus Rotich
Author-email: nicholas.rotich@gmail.com
License: MIT
Project-URL: Bug Tracker, https://github.com/pypa/alphaneural/issues
Platform: any
Classifier: License :: OSI Approved :: MIT License
Requires-Python: >=3.8
License-File: LICENSE
Requires-Dist: setuptools (>=58.1.0)
Requires-Dist: wheel (>=0.37.1)
Requires-Dist: pandas (>=1.4.2)
Requires-Dist: fire
